imas_tools/__init__.py
imas_tools/portal/__init__.py
imas_tools/portal/article.py
imas_tools/portal/interfaces.py
imas_tools/recochoku.py
imas_tools/story/__init__.py
imas_tools/story/adapter.py
imas_tools/story/gakuen_parser.py
imas_tools/story/story_csv.py
imas_tools-0.4.8.dist-info/METADATA
imas_tools-0.4.8.dist-info/WHEEL
imas_tools-0.4.8.dist-info/RECORD
