Metadata-Version: 2.1
Name: imas-tools
Version: 0.4.8
Summary: 
Author: darwintree
Author-email: 17946284+darwintree@users.noreply.github.com
Requires-Python: >=3.8
Classifier: Programming Language :: Python :: 3
Classifier: Programming Language :: Python :: 3.8
Classifier: Programming Language :: Python :: 3.9
Classifier: Programming Language :: Python :: 3.10
Classifier: Programming Language :: Python :: 3.11
Classifier: Programming Language :: Python :: 3.12
Requires-Dist: beautifulsoup4 (>=4.12.3,<5.0.0)
Requires-Dist: pytz (>=2024.1,<2025.0)
Requires-Dist: requests (>=2.32.2,<3.0.0)
Requires-Dist: typing-extensions (>=4.11.0,<5.0.0)
